physrisk/__init__.py
physrisk/container.py
physrisk/requests.py
physrisk/api/__init__.py
physrisk/api/v1/__init__.py
physrisk/api/v1/common.py
physrisk/api/v1/example_portfolios.py
physrisk/api/v1/exposure_req_resp.py
physrisk/api/v1/hazard_data.py
physrisk/api/v1/hazard_image.py
physrisk/api/v1/impact_req_resp.py
physrisk/api/v2/__init__.py
physrisk/data/__init__.py
physrisk/data/colormap_provider.py
physrisk/data/geocode.py
physrisk/data/geotiff_reader.py
physrisk/data/hazard_data_provider.py
physrisk/data/image_creator.py
physrisk/data/inventory.py
physrisk/data/inventory_reader.py
physrisk/data/pregenerated_hazard_model.py
physrisk/data/utilities.py
physrisk/data/zarr_reader.py
physrisk/data/ne_10m_admin_0_map_subunits/__init__.py
physrisk/data/ne_10m_admin_0_map_subunits/country_codes.tsv
physrisk/data/ne_10m_admin_0_map_subunits/ne_10m_admin_0_map_subunits.VERSION.txt
physrisk/data/ne_10m_admin_0_map_subunits/ne_10m_admin_0_map_subunits.cpg
physrisk/data/ne_10m_admin_0_map_subunits/ne_10m_admin_0_map_subunits.dbf
physrisk/data/ne_10m_admin_0_map_subunits/ne_10m_admin_0_map_subunits.prj
physrisk/data/ne_10m_admin_0_map_subunits/ne_10m_admin_0_map_subunits.shp
physrisk/data/ne_10m_admin_0_map_subunits/ne_10m_admin_0_map_subunits.shx
physrisk/data/static/__init__.py
physrisk/data/static/world.json
physrisk/data/static/world.py
physrisk/data/static/example_portfolios/__init__.py
physrisk/data/static/example_portfolios/mixed_small.json
physrisk/data/static/example_portfolios/power_generating_small.json
physrisk/data/static/example_portfolios/real_estate_small.json
physrisk/data/static/hazard/__init__.py
physrisk/data/static/hazard/inventory.json
physrisk/data/static/scenarios/scenario_description.py
physrisk/data/static/vulnerability/EU JRC global flood depth-damage functions.json
physrisk/data/static/vulnerability/WRI thermal power plant physical climate vulnerability factors.json
physrisk/data/static/vulnerability/__init__.py
physrisk_lib-1.6.1.dist-info/licenses/LICENSE
physrisk_lib-1.6.1.dist-info/METADATA
physrisk_lib-1.6.1.dist-info/WHEEL
physrisk_lib-1.6.1.dist-info/top_level.txt
physrisk_lib-1.6.1.dist-info/RECORD
