Metadata-Version: 2.4
Name: physrisk-lib
Version: 1.6.1
Summary: OS-Climate Physical Risk Library
Author-email: Joe Moorhouse <5102656+joemoorhouse@users.noreply.github.com>
License-Expression: Apache-2.0
Project-URL: Homepage, https://github.com/os-climate/physrisk
Project-URL: Repository, https://github.com/os-climate/physrisk
Project-URL: Downloads, https://github.com/os-climate/physrisk/releases
Project-URL: Bug Tracker, https://github.com/os-climate/physrisk/issues
Project-URL: Documentation, https://github.com/os-climate/physrisk/tree/main/docs
Project-URL: Source Code, https://github.com/os-climate/physrisk
Keywords: Physical,Climate,Risk,Finance
Classifier: Intended Audience :: Developers
Classifier: Intended Audience :: Science/Research
Classifier: Operating System :: MacOS
Classifier: Operating System :: Microsoft :: Windows
Classifier: Operating System :: Unix
Classifier: Programming Language :: Python
Classifier: Programming Language :: Python :: 3
Classifier: Programming Language :: Python :: 3 :: Only
Classifier: Programming Language :: Python :: 3.14
Classifier: Programming Language :: Python :: 3.13
Classifier: Programming Language :: Python :: 3.12
Classifier: Programming Language :: Python :: 3.11
Classifier: Programming Language :: Python :: 3.10
Classifier: Topic :: Office/Business :: Financial
Classifier: Topic :: Scientific/Engineering
Classifier: Topic :: Software Development
Requires-Python: >=3.10
License-File: LICENSE
Requires-Dist: affine>=2.4.0
Requires-Dist: aiohttp>=3.13.3
Requires-Dist: dependency-injector>=4.48.0
Requires-Dist: geopandas>=1.1.0
Requires-Dist: h3>=4.3.0
Requires-Dist: lmdbm>=0.0.6
Requires-Dist: numba>=0.61.0
Requires-Dist: numpy>=2.2.0
Requires-Dist: pint>=0.24.0
Requires-Dist: pillow>=11.3.0
Requires-Dist: pydantic>=2.11.0
Requires-Dist: pyproj>=3.7.0
Requires-Dist: python-dotenv>=1.1.0
Requires-Dist: requests>=2.32.0
Requires-Dist: scipy>=1.15.0
Requires-Dist: shapely>=2.1.0
Requires-Dist: s3fs>=2025.7.0
Requires-Dist: urllib3>=2.6.3
Requires-Dist: virtualenv>=20.36.1
Requires-Dist: zarr<3.0.0,>=2.18.0
Provides-Extra: dev
Requires-Dist: click>=8.2.3; extra == "dev"
Provides-Extra: test
Requires-Dist: openpyxl>=3.1.5; extra == "test"
Dynamic: license-file
